django_remix_icon/__init__.py
django_remix_icon/apps.py
django_remix_icon/fields.py
django_remix_icon/remix_icons.py
django_remix_icon/urls.py
django_remix_icon/views.py
django_remix_icon/widgets.py
django_remix_icon/static/django_remix_icon/css/icon_preview.css
django_remix_icon/static/django_remix_icon/css/icon_select.css
django_remix_icon/static/django_remix_icon/js/icon_select.js
django_remix_icon/templates/django_remix_icon/icon_select_widget.html
django_remix_icon/templates/django_remix_icon/icon_with_text.html
django_remix_icon/templatetags/__init__.py
django_remix_icon/templatetags/remix_icon_tags.py
django_remix_icon-2.0.2.dist-info/licenses/LICENSE
django_remix_icon-2.0.2.dist-info/METADATA
django_remix_icon-2.0.2.dist-info/WHEEL
django_remix_icon-2.0.2.dist-info/top_level.txt
django_remix_icon-2.0.2.dist-info/RECORD
