Metadata-Version: 2.4
Name: django-remix-icon
Version: 2.0.2
Summary: A simple Django package for integrating RemixIcon with Django admin and templates
Home-page: https://github.com/brktrlw/django-remix-icon
Author: Berkay Şen
Author-email: Berkay Şen <brktrl@protonmail.ch>
Maintainer-email: Berkay Şen <brktrl@protonmail.ch>
License: MIT License
Project-URL: Homepage, https://github.com/brktrlw/django-remix-icon
Project-URL: Documentation, https://django-remix-icon.readthedocs.io/
Project-URL: Repository, https://github.com/brktrlw/django-remix-icon.git
Project-URL: Issues, https://github.com/brktrlw/django-remix-icon/issues
Project-URL: Changelog, https://django-remix-icon.readthedocs.io/en/latest/changelog.html
Keywords: django,remix,icon,admin,field,widget,template,tags,ui,icons
Classifier: Development Status :: 4 - Beta
Classifier: Environment :: Web Environment
Classifier: Framework :: Django
Classifier: Framework :: Django :: 3.2
Classifier: Framework :: Django :: 4.0
Classifier: Framework :: Django :: 4.1
Classifier: Framework :: Django :: 4.2
Classifier: Framework :: Django :: 5.0
Classifier: Intended Audience :: Developers
Classifier: License :: OSI Approved :: MIT License
Classifier: Operating System :: OS Independent
Classifier: Programming Language :: Python
Classifier: Programming Language :: Python :: 3
Classifier: Programming Language :: Python :: 3 :: Only
Classifier: Programming Language :: Python :: 3.8
Classifier: Programming Language :: Python :: 3.9
Classifier: Programming Language :: Python :: 3.10
Classifier: Programming Language :: Python :: 3.11
Classifier: Programming Language :: Python :: 3.12
Classifier: Topic :: Internet :: WWW/HTTP
Classifier: Topic :: Internet :: WWW/HTTP :: Dynamic Content
Classifier: Topic :: Software Development :: Libraries :: Python Modules
Classifier: Topic :: Software Development :: User Interfaces
Requires-Python: >=3.8
License-File: LICENSE
Requires-Dist: Django>=3.2
Provides-Extra: dev
Requires-Dist: black>=22.0; extra == "dev"
Requires-Dist: isort>=5.0; extra == "dev"
Requires-Dist: flake8>=4.0; extra == "dev"
Provides-Extra: docs
Requires-Dist: Sphinx<6.0,>=4.0; extra == "docs"
Requires-Dist: sphinx-rtd-theme>=1.0; extra == "docs"
Requires-Dist: sphinx-autodoc-typehints>=1.12; extra == "docs"
Dynamic: author
Dynamic: home-page
Dynamic: license-file
Dynamic: requires-python
